setup.py
pytahoe/__init__.py
pytahoe.egg-info/PKG-INFO
pytahoe.egg-info/SOURCES.txt
pytahoe.egg-info/dependency_links.txt
pytahoe.egg-info/requires.txt
pytahoe.egg-info/top_level.txt