Metadata-Version: 1.1
Name: pytahoe
Version: 1.0.3
Summary: Python module for working with the Tahoe-LAFS filesystem.
Home-page: http://cryto.net/pytahoe
Author: Sven Slootweg
Author-email: pytahoe@cryto.net
License: UNKNOWN
Platform: UNKNOWN
Provides: pytahoe
